factorylint/__init__.py
factorylint/cli.py
factorylint/core/__init__.py
factorylint/core/config_validator.py
factorylint/core/linter.py
factorylint/core/resources.py
factorylint/core/validators.py
factorylint-0.1.11.dist-info/licenses/LICENSE
factorylint-0.1.11.dist-info/METADATA
factorylint-0.1.11.dist-info/WHEEL
factorylint-0.1.11.dist-info/entry_points.txt
factorylint-0.1.11.dist-info/top_level.txt
factorylint-0.1.11.dist-info/RECORD
