Metadata-Version: 2.4
Name: factorylint
Version: 0.1.11
Summary: A CLI tool to lint Azure Data Factory resources for naming convention compliance
Author-email: Dima Frank <dimafrank91@gmail.com>
License: MIT License
Requires-Python: >=3.9
License-File: LICENSE
Requires-Dist: click>=8.0.0
Requires-Dist: PyYAML>=6.0.3
Dynamic: license-file
